SignExtend/SignExtend.sv
module SignExtend #(
    INSTR_WIDTH = 32,
    DATA_WIDTH = 12
) (
    input logic [INSTR_WIDTH-1:0] Instr,
    input logic [DATA_WIDTH-1:0] ImmSrc,
    output logic [INSTR_WIDTH-1:0] ImmOp 
);
logic [6:0] op  = Instr[6:0];
logic [2:0] func3  = Instr[14:12];
always_comb begin
    case (op)
    // 51: 
    3: begin 
        case (func3)
            3'b010: ImmOp = {{(INSTR_WIDTH-DATA_WIDTH){ImmSrc[DATA_WIDTH-1]}},ImmSrc};
        endcase
        
    end
    19:begin 
        case (func3)
            3'b000: ImmOp = {{(INSTR_WIDTH-DATA_WIDTH){ImmSrc[DATA_WIDTH-1]}},ImmSrc};
        endcase
    end
    // 35:
    99:begin 
        case (func3)
            3'b001: ImmOp = {{(INSTR_WIDTH-DATA_WIDTH){ImmSrc[DATA_WIDTH-1]}},ImmSrc};
        endcase
    end      
    endcase


end
    
endmodule

SignExtend/SignExtend.vcd
$version Generated by VerilatedVcd $end
$date Mon Nov 21 12:53:35 2022 $end
$timescale 1ps $end

 $scope module TOP $end
  $var wire 32 % ImmOp [31:0] $end
  $var wire 12 $ ImmSrc [11:0] $end
  $var wire 32 # Instr [31:0] $end
  $scope module SignExtend $end
   $var wire 32 ) DATA_WIDTH [31:0] $end
   $var wire 32 ( INSTR_WIDTH [31:0] $end
   $var wire 32 % ImmOp [31:0] $end
   $var wire 12 $ ImmSrc [11:0] $end
   $var wire 32 # Instr [31:0] $end
   $var wire  3 ' func3 [2:0] $end
   $var wire  7 & op [6:0] $end
  $upscope $end
 $upscope $end
$enddefinitions $end


#0
b00000000000101001010001100000011 #
b000000000001 $
b00000000000000000000000000000000 %
b0000011 &
b010 '
b00000000000000000000000000100000 (
b00000000000000000000000000001100 )
#1
b00000000000000000000000000000001 %
#2
b000000000000 $
#3
b00000000000000000000000000000000 %
#4
b111111111111 $
#5
b11111111111111111111111111111111 %
#6
b111111111110 $
#7
b11111111111111111111111111111110 %
#8
b111111111101 $
#9
b11111111111111111111111111111101 %
#10
b111111111100 $
#11
b11111111111111111111111111111100 %
#12
b111111111011 $
#13
b11111111111111111111111111111011 %
#14
b111111111010 $
#15
b11111111111111111111111111111010 %
#16
b111111111001 $
#17
b11111111111111111111111111111001 %
#18
b111111111000 $
#19
b11111111111111111111111111111000 %
#20
b111111110111 $
#21
b11111111111111111111111111110111 %
#22
b111111110110 $
#23
b11111111111111111111111111110110 %
#24
b111111110101 $
#25
b11111111111111111111111111110101 %
#26
b111111110100 $
#27
b11111111111111111111111111110100 %
#28
b111111110011 $
#29
b11111111111111111111111111110011 %
#30
b111111110010 $
#31
b11111111111111111111111111110010 %
#32
b111111110001 $
#33
b11111111111111111111111111110001 %
#34
b111111110000 $
#35
b11111111111111111111111111110000 %
#36
b111111101111 $
#37
b11111111111111111111111111101111 %
#38
b111111101110 $
#39
b11111111111111111111111111101110 %
#40
b111111101101 $
#41
b11111111111111111111111111101101 %
#42
b111111101100 $
#43
b11111111111111111111111111101100 %
#44
b111111101011 $
#45
b11111111111111111111111111101011 %
#46
b111111101010 $
#47
b11111111111111111111111111101010 %
#48
b111111101001 $
#49
b11111111111111111111111111101001 %
#50
b111111101000 $
#51
b11111111111111111111111111101000 %
#52
b111111100111 $
#53
b11111111111111111111111111100111 %
#54
b111111100110 $
#55
b11111111111111111111111111100110 %
#56
b111111100101 $
#57
b11111111111111111111111111100101 %
#58
b111111100100 $
#59
b11111111111111111111111111100100 %
#60
b111111100011 $
#61
b11111111111111111111111111100011 %
#62
b111111100010 $
#63
b11111111111111111111111111100010 %
#64
b111111100001 $
#65
b11111111111111111111111111100001 %
#66
b111111100000 $
#67
b11111111111111111111111111100000 %
#68
b111111011111 $
#69
b11111111111111111111111111011111 %
#70
b111111011110 $
#71
b11111111111111111111111111011110 %
#72
b111111011101 $
#73
b11111111111111111111111111011101 %
#74
b111111011100 $
#75
b11111111111111111111111111011100 %
#76
b111111011011 $
#77
b11111111111111111111111111011011 %
#78
b111111011010 $
#79
b11111111111111111111111111011010 %
#80
b111111011001 $
#81
b11111111111111111111111111011001 %
#82
b111111011000 $
#83
b11111111111111111111111111011000 %
#84
b111111010111 $
#85
b11111111111111111111111111010111 %
#86
b111111010110 $
#87
b11111111111111111111111111010110 %
#88
b111111010101 $
#89
b11111111111111111111111111010101 %
#90
b111111010100 $
#91
b11111111111111111111111111010100 %
#92
b111111010011 $
#93
b11111111111111111111111111010011 %
#94
b111111010010 $
#95
b11111111111111111111111111010010 %
#96
b111111010001 $
#97
b11111111111111111111111111010001 %
#98
b111111010000 $
#99
b11111111111111111111111111010000 %
#100
b111111001111 $
#101
b11111111111111111111111111001111 %
#102
b111111001110 $
#103
b11111111111111111111111111001110 %
#104
b111111001101 $
#105
b11111111111111111111111111001101 %
#106
b111111001100 $
#107
b11111111111111111111111111001100 %
#108
b111111001011 $
#109
b11111111111111111111111111001011 %
#110
b111111001010 $
#111
b11111111111111111111111111001010 %
#112
b111111001001 $
#113
b11111111111111111111111111001001 %
#114
b111111001000 $
#115
b11111111111111111111111111001000 %
#116
b111111000111 $
#117
b11111111111111111111111111000111 %
#118
b111111000110 $
#119
b11111111111111111111111111000110 %
#120
b111111000101 $
#121
b11111111111111111111111111000101 %
#122
b111111000100 $
#123
b11111111111111111111111111000100 %
#124
b111111000011 $
#125
b11111111111111111111111111000011 %
#126
b111111000010 $
#127
b11111111111111111111111111000010 %
#128
b111111000001 $
#129
b11111111111111111111111111000001 %
#130
b111111000000 $
#131
b11111111111111111111111111000000 %
#132
b111110111111 $
#133
b11111111111111111111111110111111 %
#134
b111110111110 $
#135
b11111111111111111111111110111110 %
#136
b111110111101 $
#137
b11111111111111111111111110111101 %
#138
b111110111100 $
#139
b11111111111111111111111110111100 %
#140
b111110111011 $
#141
b11111111111111111111111110111011 %
#142
b111110111010 $
#143
b11111111111111111111111110111010 %
#144
b111110111001 $
#145
b11111111111111111111111110111001 %
#146
b111110111000 $
#147
b11111111111111111111111110111000 %
#148
b111110110111 $
#149
b11111111111111111111111110110111 %
#150
b111110110110 $
#151
b11111111111111111111111110110110 %
#152
b111110110101 $
#153
b11111111111111111111111110110101 %
#154
b111110110100 $
#155
b11111111111111111111111110110100 %
#156
b111110110011 $
#157
b11111111111111111111111110110011 %
#158
b111110110010 $
#159
b11111111111111111111111110110010 %
#160
b111110110001 $
#161
b11111111111111111111111110110001 %
#162
b111110110000 $
#163
b11111111111111111111111110110000 %
#164
b111110101111 $
#165
b11111111111111111111111110101111 %
#166
b111110101110 $
#167
b11111111111111111111111110101110 %
#168
b111110101101 $
#169
b11111111111111111111111110101101 %
#170
b111110101100 $
#171
b11111111111111111111111110101100 %
#172
b111110101011 $
#173
b11111111111111111111111110101011 %
#174
b111110101010 $
#175
b11111111111111111111111110101010 %
#176
b111110101001 $
#177
b11111111111111111111111110101001 %
#178
b111110101000 $
#179
b11111111111111111111111110101000 %
#180
b111110100111 $
#181
b11111111111111111111111110100111 %
#182
b111110100110 $
#183
b11111111111111111111111110100110 %
#184
b111110100101 $
#185
b11111111111111111111111110100101 %
#186
b111110100100 $
#187
b11111111111111111111111110100100 %
#188
b111110100011 $
#189
b11111111111111111111111110100011 %
#190
b111110100010 $
#191
b11111111111111111111111110100010 %
#192
b111110100001 $
#193
b11111111111111111111111110100001 %
#194
b111110100000 $
#195
b11111111111111111111111110100000 %
#196
b111110011111 $
#197
b11111111111111111111111110011111 %
#198
b111110011110 $
#199
b11111111111111111111111110011110 %
#200
b111110011101 $
#201
b11111111111111111111111110011101 %
#202
b111110011100 $
#203
b11111111111111111111111110011100 %
#204
b111110011011 $
#205
b11111111111111111111111110011011 %
#206
b111110011010 $
#207
b11111111111111111111111110011010 %
#208
b111110011001 $
#209
b11111111111111111111111110011001 %
#210
b111110011000 $
#211
b11111111111111111111111110011000 %
#212
b111110010111 $
#213
b11111111111111111111111110010111 %
#214
b111110010110 $
#215
b11111111111111111111111110010110 %
#216
b111110010101 $
#217
b11111111111111111111111110010101 %
#218
b111110010100 $
#219
b11111111111111111111111110010100 %
#220
b111110010011 $
#221
b11111111111111111111111110010011 %
#222
b111110010010 $
#223
b11111111111111111111111110010010 %
#224
b111110010001 $
#225
b11111111111111111111111110010001 %
#226
b111110010000 $
#227
b11111111111111111111111110010000 %
#228
b111110001111 $
#229
b11111111111111111111111110001111 %
#230
b111110001110 $
#231
b11111111111111111111111110001110 %
#232
b111110001101 $
#233
b11111111111111111111111110001101 %
#234
b111110001100 $
#235
b11111111111111111111111110001100 %
#236
b111110001011 $
#237
b11111111111111111111111110001011 %
#238
b111110001010 $
#239
b11111111111111111111111110001010 %
#240
b111110001001 $
#241
b11111111111111111111111110001001 %
#242
b111110001000 $
#243
b11111111111111111111111110001000 %
#244
b111110000111 $
#245
b11111111111111111111111110000111 %
#246
b111110000110 $
#247
b11111111111111111111111110000110 %
#248
b111110000101 $
#249
b11111111111111111111111110000101 %
#250
b111110000100 $
#251
b11111111111111111111111110000100 %
#252
b111110000011 $
#253
b11111111111111111111111110000011 %
#254
b111110000010 $
#255
b11111111111111111111111110000010 %
#256
b111110000001 $
#257
b11111111111111111111111110000001 %
#258
b111110000000 $
#259
b11111111111111111111111110000000 %
#260
b111101111111 $
#261
b11111111111111111111111101111111 %
#262
b111101111110 $
#263
b11111111111111111111111101111110 %
#264
b111101111101 $
#265
b11111111111111111111111101111101 %
#266
b111101111100 $
#267
b11111111111111111111111101111100 %
#268
b111101111011 $
#269
b11111111111111111111111101111011 %
#270
b111101111010 $
#271
b11111111111111111111111101111010 %
#272
b111101111001 $
#273
b11111111111111111111111101111001 %
#274
b111101111000 $
#275
b11111111111111111111111101111000 %
#276
b111101110111 $
#277
b11111111111111111111111101110111 %
#278
b111101110110 $
#279
b11111111111111111111111101110110 %
#280
b111101110101 $
#281
b11111111111111111111111101110101 %
#282
b111101110100 $
#283
b11111111111111111111111101110100 %
#284
b111101110011 $
#285
b11111111111111111111111101110011 %
#286
b111101110010 $
#287
b11111111111111111111111101110010 %
#288
b111101110001 $
#289
b11111111111111111111111101110001 %
#290
b111101110000 $
#291
b11111111111111111111111101110000 %
#292
b111101101111 $
#293
b11111111111111111111111101101111 %
#294
b111101101110 $
#295
b11111111111111111111111101101110 %
#296
b111101101101 $
#297
b11111111111111111111111101101101 %
#298
b111101101100 $
#299
b11111111111111111111111101101100 %
#300
b111101101011 $
#301
b11111111111111111111111101101011 %
#302
b111101101010 $
#303
b11111111111111111111111101101010 %
#304
b111101101001 $
#305
b11111111111111111111111101101001 %
#306
b111101101000 $
#307
b11111111111111111111111101101000 %
#308
b111101100111 $
#309
b11111111111111111111111101100111 %
#310
b111101100110 $
#311
b11111111111111111111111101100110 %
#312
b111101100101 $
#313
b11111111111111111111111101100101 %
#314
b111101100100 $
#315
b11111111111111111111111101100100 %
#316
b111101100011 $
#317
b11111111111111111111111101100011 %
#318
b111101100010 $
#319
b11111111111111111111111101100010 %
#320
b111101100001 $
#321
b11111111111111111111111101100001 %
#322
b111101100000 $
#323
b11111111111111111111111101100000 %
#324
b111101011111 $
#325
b11111111111111111111111101011111 %
#326
b111101011110 $
#327
b11111111111111111111111101011110 %
#328
b111101011101 $
#329
b11111111111111111111111101011101 %
#330
b111101011100 $
#331
b11111111111111111111111101011100 %
#332
b111101011011 $
#333
b11111111111111111111111101011011 %
#334
b111101011010 $
#335
b11111111111111111111111101011010 %
#336
b111101011001 $
#337
b11111111111111111111111101011001 %
#338
b111101011000 $
#339
b11111111111111111111111101011000 %
#340
b111101010111 $
#341
b11111111111111111111111101010111 %
#342
b111101010110 $
#343
b11111111111111111111111101010110 %
#344
b111101010101 $
#345
b11111111111111111111111101010101 %
#346
b111101010100 $
#347
b11111111111111111111111101010100 %
#348
b111101010011 $
#349
b11111111111111111111111101010011 %
#350
b111101010010 $
#351
b11111111111111111111111101010010 %
#352
b111101010001 $
#353
b11111111111111111111111101010001 %
#354
b111101010000 $
#355
b11111111111111111111111101010000 %
#356
b111101001111 $
#357
b11111111111111111111111101001111 %
#358
b111101001110 $
#359
b11111111111111111111111101001110 %
#360
b111101001101 $
#361
b11111111111111111111111101001101 %
#362
b111101001100 $
#363
b11111111111111111111111101001100 %
#364
b111101001011 $
#365
b11111111111111111111111101001011 %
#366
b111101001010 $
#367
b11111111111111111111111101001010 %
#368
b111101001001 $
#369
b11111111111111111111111101001001 %
#370
b111101001000 $
#371
b11111111111111111111111101001000 %
#372
b111101000111 $
#373
b11111111111111111111111101000111 %
#374
b111101000110 $
#375
b11111111111111111111111101000110 %
#376
b111101000101 $
#377
b11111111111111111111111101000101 %
#378
b111101000100 $
#379
b11111111111111111111111101000100 %
#380
b111101000011 $
#381
b11111111111111111111111101000011 %
#382
b111101000010 $
#383
b11111111111111111111111101000010 %
#384
b111101000001 $
#385
b11111111111111111111111101000001 %
#386
b111101000000 $
#387
b11111111111111111111111101000000 %
#388
b111100111111 $
#389
b11111111111111111111111100111111 %
#390
b111100111110 $
#391
b11111111111111111111111100111110 %
#392
b111100111101 $
#393
b11111111111111111111111100111101 %
#394
b111100111100 $
#395
b11111111111111111111111100111100 %
#396
b111100111011 $
#397
b11111111111111111111111100111011 %
#398
b111100111010 $
#399
b11111111111111111111111100111010 %
#400
b111100111001 $
#401
b11111111111111111111111100111001 %
#402
b111100111000 $
#403
b11111111111111111111111100111000 %
#404
b111100110111 $
#405
b11111111111111111111111100110111 %
#406
b111100110110 $
#407
b11111111111111111111111100110110 %
#408
b111100110101 $
#409
b11111111111111111111111100110101 %
#410
b111100110100 $
#411
b11111111111111111111111100110100 %
#412
b111100110011 $
#413
b11111111111111111111111100110011 %
#414
b111100110010 $
#415
b11111111111111111111111100110010 %
#416
b111100110001 $
#417
b11111111111111111111111100110001 %
#418
b111100110000 $
#419
b11111111111111111111111100110000 %
#420
b111100101111 $
#421
b11111111111111111111111100101111 %
#422
b111100101110 $
#423
b11111111111111111111111100101110 %
#424
b111100101101 $
#425
b11111111111111111111111100101101 %
#426
b111100101100 $
#427
b11111111111111111111111100101100 %
#428
b111100101011 $
#429
b11111111111111111111111100101011 %
#430
b111100101010 $
#431
b11111111111111111111111100101010 %
#432
b111100101001 $
#433
b11111111111111111111111100101001 %
#434
b111100101000 $
#435
b11111111111111111111111100101000 %
#436
b111100100111 $
#437
b11111111111111111111111100100111 %
#438
b111100100110 $
#439
b11111111111111111111111100100110 %
#440
b111100100101 $
#441
b11111111111111111111111100100101 %
#442
b111100100100 $
#443
b11111111111111111111111100100100 %
#444
b111100100011 $
#445
b11111111111111111111111100100011 %
#446
b111100100010 $
#447
b11111111111111111111111100100010 %
#448
b111100100001 $
#449
b11111111111111111111111100100001 %
#450
b111100100000 $
#451
b11111111111111111111111100100000 %
#452
b111100011111 $
#453
b11111111111111111111111100011111 %
#454
b111100011110 $
#455
b11111111111111111111111100011110 %
#456
b111100011101 $
#457
b11111111111111111111111100011101 %
#458
b111100011100 $
#459
b11111111111111111111111100011100 %
#460
b111100011011 $
#461
b11111111111111111111111100011011 %
#462
b111100011010 $
#463
b11111111111111111111111100011010 %
#464
b111100011001 $
#465
b11111111111111111111111100011001 %
#466
b111100011000 $
#467
b11111111111111111111111100011000 %
#468
b111100010111 $
#469
b11111111111111111111111100010111 %
#470
b111100010110 $
#471
b11111111111111111111111100010110 %
#472
b111100010101 $
#473
b11111111111111111111111100010101 %
#474
b111100010100 $
#475
b11111111111111111111111100010100 %
#476
b111100010011 $
#477
b11111111111111111111111100010011 %
#478
b111100010010 $
#479
b11111111111111111111111100010010 %
#480
b111100010001 $
#481
b11111111111111111111111100010001 %
#482
b111100010000 $
#483
b11111111111111111111111100010000 %
#484
b111100001111 $
#485
b11111111111111111111111100001111 %
#486
b111100001110 $
#487
b11111111111111111111111100001110 %
#488
b111100001101 $
#489
b11111111111111111111111100001101 %
#490
b111100001100 $
#491
b11111111111111111111111100001100 %
#492
b111100001011 $
#493
b11111111111111111111111100001011 %
#494
b111100001010 $
#495
b11111111111111111111111100001010 %
#496
b111100001001 $
#497
b11111111111111111111111100001001 %
#498
b111100001000 $
#499
b11111111111111111111111100001000 %
#500
b111100000111 $
#501
b11111111111111111111111100000111 %
#502
b111100000110 $
#503
b11111111111111111111111100000110 %
#504
b111100000101 $
#505
b11111111111111111111111100000101 %
#506
b111100000100 $
#507
b11111111111111111111111100000100 %
#508
b111100000011 $
#509
b11111111111111111111111100000011 %
#510
b111100000010 $
#511
b11111111111111111111111100000010 %
#512
b111100000001 $
#513
b11111111111111111111111100000001 %
#514
b111100000000 $
#515
b11111111111111111111111100000000 %
#516
b111011111111 $
#517
b11111111111111111111111011111111 %
#518
b111011111110 $
#519
b11111111111111111111111011111110 %
#520
b111011111101 $
#521
b11111111111111111111111011111101 %
#522
b111011111100 $
#523
b11111111111111111111111011111100 %
#524
b111011111011 $
#525
b11111111111111111111111011111011 %
#526
b111011111010 $
#527
b11111111111111111111111011111010 %
#528
b111011111001 $
#529
b11111111111111111111111011111001 %
#530
b111011111000 $
#531
b11111111111111111111111011111000 %
#532
b111011110111 $
#533
b11111111111111111111111011110111 %
#534
b111011110110 $
#535
b11111111111111111111111011110110 %
#536
b111011110101 $
#537
b11111111111111111111111011110101 %
#538
b111011110100 $
#539
b11111111111111111111111011110100 %
#540
b111011110011 $
#541
b11111111111111111111111011110011 %
#542
b111011110010 $
#543
b11111111111111111111111011110010 %
#544
b111011110001 $
#545
b11111111111111111111111011110001 %
#546
b111011110000 $
#547
b11111111111111111111111011110000 %
#548
b111011101111 $
#549
b11111111111111111111111011101111 %
#550
b111011101110 $
#551
b11111111111111111111111011101110 %
#552
b111011101101 $
#553
b11111111111111111111111011101101 %
#554
b111011101100 $
#555
b11111111111111111111111011101100 %
#556
b111011101011 $
#557
b11111111111111111111111011101011 %
#558
b111011101010 $
#559
b11111111111111111111111011101010 %
#560
b111011101001 $
#561
b11111111111111111111111011101001 %
#562
b111011101000 $
#563
b11111111111111111111111011101000 %
#564
b111011100111 $
#565
b11111111111111111111111011100111 %
#566
b111011100110 $
#567
b11111111111111111111111011100110 %
#568
b111011100101 $
#569
b11111111111111111111111011100101 %
#570
b111011100100 $
#571
b11111111111111111111111011100100 %
#572
b111011100011 $
#573
b11111111111111111111111011100011 %
#574
b111011100010 $
#575
b11111111111111111111111011100010 %
#576
b111011100001 $
#577
b11111111111111111111111011100001 %
#578
b111011100000 $
#579
b11111111111111111111111011100000 %
#580
b111011011111 $
#581
b11111111111111111111111011011111 %
#582
b111011011110 $
#583
b11111111111111111111111011011110 %
#584
b111011011101 $
#585
b11111111111111111111111011011101 %
#586
b111011011100 $
#587
b11111111111111111111111011011100 %
#588
b111011011011 $
#589
b11111111111111111111111011011011 %
#590
b111011011010 $
#591
b11111111111111111111111011011010 %
#592
b111011011001 $
#593
b11111111111111111111111011011001 %
#594
b111011011000 $
#595
b11111111111111111111111011011000 %
#596
b111011010111 $
#597
b11111111111111111111111011010111 %
#598
b111011010110 $
#599
b11111111111111111111111011010110 %
